AUTHORS
ChangeLog
LICENSE.txt
README.md
assembly.xml
pom.xml
setup.py
demo/click_in/testsuite_clickin.txt
demo/click_in/html/click_in_demo.html
demo/click_in/img/left_area.png
demo/click_in/img/right_area.png
demo/click_in/img/target.png
demo/hello_world/ruby_demo.rb
demo/hello_world/testsuite_sikuli_demo.txt
demo/hello_world/img/close.png
demo/hello_world/img/dont_save.png
demo/hello_world/img/notepad.png
demo/hello_world/img/notepad_title.png
demo/hello_world/img/notepad_workspace.png
demo/hello_world/img/search_input.png
demo/hello_world/img/windows_start_menu.png
docs/SikuliLibrary.html
docs/img/architecture.png
docs/img/log.png
myrobotlibrary.egg-info/PKG-INFO
myrobotlibrary.egg-info/SOURCES.txt
myrobotlibrary.egg-info/dependency_links.txt
myrobotlibrary.egg-info/pbr.json
myrobotlibrary.egg-info/top_level.txt
src/java/META-INF/MANIFEST.MF
src/java/com/github/rainmanwy/robotframework/sikulilib/SikuliLibrary.java
src/java/com/github/rainmanwy/robotframework/sikulilib/exceptions/ScreenOperationException.java
src/java/com/github/rainmanwy/robotframework/sikulilib/exceptions/TimeoutException.java
src/java/com/github/rainmanwy/robotframework/sikulilib/keywords/ScreenKeywords.java
src/java/com/github/rainmanwy/robotframework/sikulilib/utils/CaptureFolder.java
src/python/__init__.py
src/python/sikuli.py
src/python/version.py