Metadata-Version: 1.0
Name: myrobotlibrary
Version: 0.0.4
Summary: just a simple test
Home-page: UNKNOWN
Author: jim
Author-email: jim@126.com
License: MIT License
Keywords: simple,test
Platform: any
